[
  {
    "acceleration": {
      "accelerationX": 0.0,
      "accelerationY": 0.0
    },
    "jsTypeEntity": {
      "typeEntity": "Material"
    },
    "visible": {
      "visible": true
    },
    "collidable": {
      "collidable": true
    },
    "position": {
      "point": {
        "x": 150.0,
        "y": 30.0
      }
    },
    "dimension": {
      "radius": 5
    },
    "speed": {
      "speedX": 0.1,
      "speedY": 0.5
    }
  },
  {
    "acceleration": {
      "accelerationX": 0.0,
      "accelerationY": 0.0
    },
    "jsTypeEntity": {
      "typeEntity": "Material"
    },
    "visible": {
      "visible": true
    },
    "collidable": {
      "collidable": true
    },
    "position": {
      "point": {
        "x": 100.0,
        "y": 90.0
      }
    },
    "dimension": {
      "radius": 15
    },
    "speed": {
      "speedX": 0.1,
      "speedY": 0.25
    }
  },
  {
    "acceleration": {
      "accelerationX": 0.0,
      "accelerationY": 0.0
    },
    "jsTypeEntity": {
      "typeEntity": "Material"
    },
    "visible": {
      "visible": true
    },
    "collidable": {
      "collidable": true
    },
    "position": {
      "point": {
        "x": 10.0,
        "y": 100.0
      }
    },
    "dimension": {
      "radius": 10
    },
    "speed": {
      "speedX": 0.2,
      "speedY": 1
    }
  },
  {
    "acceleration": {
      "accelerationX": 0.0,
      "accelerationY": 0.0
    },
    "jsTypeEntity": {
      "typeEntity": "Material"
    },
    "visible": {
      "visible": true
    },
    "collidable": {
      "collidable": true
    },
    "position": {
      "point": {
        "x": 8.0,
        "y": 80.0
      }
    },
    "dimension": {
      "radius": 35
    },
    "speed": {
      "speedX": 0.3,
      "speedY": 0.5
    }
  },
  {
    "acceleration": {
      "accelerationX": 0.0,
      "accelerationY": 0.0
    },
    "jsTypeEntity": {
      "typeEntity": "Material"
    },
    "visible": {
      "visible": true
    },
    "collidable": {
      "collidable": true
    },
    "position": {
      "point": {
        "x": 40.0,
        "y": 25.0
      }
    },
    "dimension": {
      "radius": 10
    },
    "speed": {
      "speedX": 0.1,
      "speedY": 0.99
    }
  },
  {
    "acceleration": {
      "accelerationX": 0.0,
      "accelerationY": 0.0
    },
    "jsTypeEntity": {
      "typeEntity": "Material"
    },
    "visible": {
      "visible": true
    },
    "collidable": {
      "collidable": true
    },
    "position": {
      "point": {
        "x": 10.0,
        "y": 30.0
      }
    },
    "dimension": {
      "radius": 8
    },
    "speed": {
      "speedX": 0.3,
      "speedY": 0.8
    }
  }
]
